sigstrike/__init__.py
sigstrike/_sigstrike.cpython-312-aarch64-linux-gnu.so
sigstrike/py.typed
sigstrike.libs/libcrypto-3dc39733.so.1.1.1k
sigstrike.libs/libssl-b6e07dfa.so.1.1.1k
sigstrike-0.1.5.dist-info/METADATA
sigstrike-0.1.5.dist-info/WHEEL
sigstrike-0.1.5.dist-info/entry_points.txt
sigstrike-0.1.5.dist-info/top_level.txt
sigstrike-0.1.5.dist-info/RECORD
sigstrike-0.1.5.dist-info/licenses/LICENSE
sigstrike-0.1.5.dist-info/sboms/auditwheel.cdx.json
