Metadata-Version: 2.4
Name: sigstrike
Version: 0.1.5
Summary: Cobalt Strike beacon crawler and parser.
Author-email: Artem Golubin <me@rushter.com>
License-Expression: MIT
Requires-Python: >=3.9
License-File: LICENSE
Dynamic: license-file
